azure/ai/agentserver/__init__.py
azure/ai/agentserver/core/__init__.py
azure/ai/agentserver/core/_version.py
azure/ai/agentserver/core/constants.py
azure/ai/agentserver/core/logger.py
azure/ai/agentserver/core/py.typed
azure/ai/agentserver/core/client/__init__.py
azure/ai/agentserver/core/client/tools/__init__.py
azure/ai/agentserver/core/client/tools/_client.py
azure/ai/agentserver/core/client/tools/_configuration.py
azure/ai/agentserver/core/client/tools/_exceptions.py
azure/ai/agentserver/core/client/tools/_model_base.py
azure/ai/agentserver/core/client/tools/_utils/_model_base.py
azure/ai/agentserver/core/client/tools/aio/__init__.py
azure/ai/agentserver/core/client/tools/aio/_client.py
azure/ai/agentserver/core/client/tools/aio/_configuration.py
azure/ai/agentserver/core/client/tools/aio/operations/_operations.py
azure/ai/agentserver/core/client/tools/operations/_operations.py
azure/ai/agentserver/core/models/__init__.py
azure/ai/agentserver/core/models/_create_response.py
azure/ai/agentserver/core/models/openai/__init__.py
azure/ai/agentserver/core/models/projects/__init__.py
azure/ai/agentserver/core/models/projects/_enums.py
azure/ai/agentserver/core/models/projects/_models.py
azure/ai/agentserver/core/models/projects/_patch.py
azure/ai/agentserver/core/models/projects/_patch_evaluations.py
azure/ai/agentserver/core/models/projects/_utils/__init__.py
azure/ai/agentserver/core/models/projects/_utils/model_base.py
azure/ai/agentserver/core/models/projects/_utils/serialization.py
azure/ai/agentserver/core/server/__init__.py
azure/ai/agentserver/core/server/base.py
azure/ai/agentserver/core/server/common/__init__.py
azure/ai/agentserver/core/server/common/agent_run_context.py
azure/ai/agentserver/core/server/common/id_generator/__init__.py
azure/ai/agentserver/core/server/common/id_generator/foundry_id_generator.py
azure/ai/agentserver/core/server/common/id_generator/id_generator.py
azure_ai_agentserver_core-1.0.0b5.dist-info/licenses/LICENSE
azure_ai_agentserver_core-1.0.0b5.dist-info/METADATA
azure_ai_agentserver_core-1.0.0b5.dist-info/WHEEL
azure_ai_agentserver_core-1.0.0b5.dist-info/top_level.txt
azure_ai_agentserver_core-1.0.0b5.dist-info/RECORD
