Metadata-Version: 2.4
Name: azure-ai-agentserver-core
Version: 1.0.0b5
Summary: Agents server adapter for Azure AI
Author-email: Microsoft Corporation <azpysdkhelp@microsoft.com>
License-Expression: MIT
Project-URL: repository, https://github.com/Azure/azure-sdk-for-python
Keywords: azure,azure sdk
Classifier: Programming Language :: Python
Classifier: Programming Language :: Python :: 3 :: Only
Classifier: Programming Language :: Python :: 3
Classifier: Programming Language :: Python :: 3.10
Classifier: Programming Language :: Python :: 3.11
Classifier: Programming Language :: Python :: 3.12
Classifier: Programming Language :: Python :: 3.13
Requires-Python: >=3.10
License-File: LICENSE
Requires-Dist: azure-monitor-opentelemetry>=1.5.0
Requires-Dist: azure-ai-projects==1.1.0b4
Requires-Dist: azure-ai-agents==1.2.0b5
Requires-Dist: azure-core>=1.35.0
Requires-Dist: azure-identity
Requires-Dist: openai>=1.80.0
Requires-Dist: opentelemetry-api>=1.35
Requires-Dist: opentelemetry-exporter-otlp-proto-http
Requires-Dist: starlette>=0.45.0
Requires-Dist: uvicorn>=0.31.0
Dynamic: license-file
